{
  "_id": "692da8fb5e56651e018a22b1",
  "memberships": [
    {
      "type": "SIMPLE_REFSET",
      "referencedComponentId": "6215006",
      "refset": {
        "conceptId": "1127601000000107",
        "defaultTerm": "Healthcare matters simple reference set (foundation metadata concept)",
        "definitionStatus": "Primitive",
        "statedDescendants": 0,
        "inferredDescendants": 0,
        "active": true,
        "effectiveTime": "20191001",
        "module": "999000021000000109"
      },
      "uuid": "7d915748-ade1-480b-adff-14da32774c7e",
      "active": true,
      "effectiveTime": "20191001",
      "module": "999000021000000109"
    },
    {
      "type": "SIMPLEMAP",
      "referencedComponentId": "6215006",
      "refset": {
        "conceptId": "900000000000497000",
        "defaultTerm": "CTV3 to SNOMED CT simple map reference set (foundation metadata concept)",
        "definitionStatus": "Primitive",
        "statedDescendants": 0,
        "inferredDescendants": 0,
        "active": true,
        "effectiveTime": "20020131",
        "module": "900000000000012004"
      },
      "otherValue": "J6610",
      "uuid": "28476daf-a89e-5b22-b6e3-bbbe136d80ba",
      "active": true,
      "effectiveTime": "20020131",
      "module": "900000000000207008"
    },
    {
      "type": "ASSOCIATION",
      "referencedComponentId": "6215006",
      "refset": {
        "conceptId": "1322291000000109",
        "defaultTerm": "National Health Service Care Record Element association reference set (foundation metadata concept)",
        "definitionStatus": "Primitive",
        "statedDescendants": 0,
        "inferredDescendants": 0,
        "active": true,
        "effectiveTime": "20200513",
        "module": "999000041000000102"
      },
      "cidValue": {
        "conceptId": "163001000000103",
        "defaultTerm": "Diagnoses - care record element (record artifact)",
        "definitionStatus": "Primitive",
        "statedDescendants": 0,
        "inferredDescendants": 0,
        "active": true,
        "effectiveTime": "20040731",
        "module": "999000011000000103"
      },
      "uuid": "fed86eab-96ed-11ea-bbef-08002728e8ff",
      "active": true,
      "effectiveTime": "20200513",
      "module": "999000031000000106"
    }
  ],
  "descriptions": [
    {
      "descriptionId": "11316014",
      "conceptId": "6215006",
      "type": {
        "conceptId": "900000000000013009",
        "defaultTerm": "Synonym (core metadata concept)",
        "definitionStatus": "Primitive",
        "statedDescendants": 0,
        "inferredDescendants": 0,
        "active": true,
        "effectiveTime": "20020131",
        "module": "900000000000012004"
      },
      "lang": "en",
      "term": "Acute cholangitis",
      "length": 17,
      "ics": {
        "conceptId": "900000000000448009",
        "defaultTerm": "Entire term case insensitive (core metadata concept)",
        "definitionStatus": "Primitive",
        "statedDescendants": 0,
        "inferredDescendants": 0,
        "active": true,
        "effectiveTime": "20020131",
        "module": "900000000000012004"
      },
      "langMemberships": [
        {
          "descriptionId": "11316014",
          "refset": {
            "conceptId": "900000000000508004",
            "defaultTerm": "Great Britain English language reference set (foundation metadata concept)",
            "definitionStatus": "Primitive",
            "statedDescendants": 0,
            "inferredDescendants": 0,
            "active": true,
            "effectiveTime": "20020131",
            "module": "900000000000012004"
          },
          "acceptability": {
            "conceptId": "900000000000548007",
            "defaultTerm": "Preferred (foundation metadata concept)",
            "definitionStatus": "Primitive",
            "statedDescendants": 0,
            "inferredDescendants": 0,
            "active": true,
            "effectiveTime": "20020131",
            "module": "900000000000012004"
          },
          "uuid": "90686596-fa53-563a-87ce-3bc3be82d156",
          "active": true,
          "effectiveTime": "20020131",
          "module": "900000000000207008"
        },
        {
          "descriptionId": "11316014",
          "refset": {
            "conceptId": "900000000000509007",
            "defaultTerm": "United States of America English language reference set (foundation metadata concept)",
            "definitionStatus": "Primitive",
            "statedDescendants": 0,
            "inferredDescendants": 0,
            "active": true,
            "effectiveTime": "20020131",
            "module": "900000000000012004"
          },
          "acceptability": {
            "conceptId": "900000000000548007",
            "defaultTerm": "Preferred (foundation metadata concept)",
            "definitionStatus": "Primitive",
            "statedDescendants": 0,
            "inferredDescendants": 0,
            "active": true,
            "effectiveTime": "20020131",
            "module": "900000000000012004"
          },
          "uuid": "94dd04b9-3b55-5af1-ab8e-d02db68079fb",
          "active": true,
          "effectiveTime": "20020131",
          "module": "900000000000207008"
        },
        {
          "descriptionId": "11316014",
          "refset": {
            "conceptId": "999001261000000100",
            "defaultTerm": "National Health Service realm language reference set (clinical part) (foundation metadata concept)",
            "definitionStatus": "Primitive",
            "statedDescendants": 0,
            "inferredDescendants": 0,
            "active": true,
            "effectiveTime": "20190601",
            "module": "999000041000000102"
          },
          "acceptability": {
            "conceptId": "900000000000548007",
            "defaultTerm": "Preferred (foundation metadata concept)",
            "definitionStatus": "Primitive",
            "statedDescendants": 0,
            "inferredDescendants": 0,
            "active": true,
            "effectiveTime": "20020131",
            "module": "900000000000012004"
          },
          "uuid": "b0857d8c-0a52-5bfb-9238-d1c92f8132c4",
          "active": true,
          "effectiveTime": "20190601",
          "module": "999000041000000102"
        }
      ],
      "active": true,
      "effectiveTime": "20170731",
      "module": "900000000000207008"
    },
    {
      "descriptionId": "801291019",
      "conceptId": "6215006",
      "type": {
        "conceptId": "900000000000003001",
        "defaultTerm": "Fully specified name (core metadata concept)",
        "definitionStatus": "Primitive",
        "statedDescendants": 0,
        "inferredDescendants": 0,
        "active": true,
        "effectiveTime": "20020131",
        "module": "900000000000012004"
      },
      "lang": "en",
      "term": "Acute cholangitis (disorder)",
      "length": 28,
      "ics": {
        "conceptId": "900000000000448009",
        "defaultTerm": "Entire term case insensitive (core metadata concept)",
        "definitionStatus": "Primitive",
        "statedDescendants": 0,
        "inferredDescendants": 0,
        "active": true,
        "effectiveTime": "20020131",
        "module": "900000000000012004"
      },
      "langMemberships": [
        {
          "descriptionId": "801291019",
          "refset": {
            "conceptId": "999001261000000100",
            "defaultTerm": "National Health Service realm language reference set (clinical part) (foundation metadata concept)",
            "definitionStatus": "Primitive",
            "statedDescendants": 0,
            "inferredDescendants": 0,
            "active": true,
            "effectiveTime": "20190601",
            "module": "999000041000000102"
          },
          "acceptability": {
            "conceptId": "900000000000548007",
            "defaultTerm": "Preferred (foundation metadata concept)",
            "definitionStatus": "Primitive",
            "statedDescendants": 0,
            "inferredDescendants": 0,
            "active": true,
            "effectiveTime": "20020131",
            "module": "900000000000012004"
          },
          "uuid": "5b4d5fe6-e259-5936-9b56-e5dd03dd7ea5",
          "active": true,
          "effectiveTime": "20190601",
          "module": "999000041000000102"
        },
        {
          "descriptionId": "801291019",
          "refset": {
            "conceptId": "900000000000508004",
            "defaultTerm": "Great Britain English language reference set (foundation metadata concept)",
            "definitionStatus": "Primitive",
            "statedDescendants": 0,
            "inferredDescendants": 0,
            "active": true,
            "effectiveTime": "20020131",
            "module": "900000000000012004"
          },
          "acceptability": {
            "conceptId": "900000000000548007",
            "defaultTerm": "Preferred (foundation metadata concept)",
            "definitionStatus": "Primitive",
            "statedDescendants": 0,
            "inferredDescendants": 0,
            "active": true,
            "effectiveTime": "20020131",
            "module": "900000000000012004"
          },
          "uuid": "90160cb1-5d64-55ec-ac7a-ef5e6cf2e70d",
          "active": true,
          "effectiveTime": "20020131",
          "module": "900000000000207008"
        },
        {
          "descriptionId": "801291019",
          "refset": {
            "conceptId": "900000000000509007",
            "defaultTerm": "United States of America English language reference set (foundation metadata concept)",
            "definitionStatus": "Primitive",
            "statedDescendants": 0,
            "inferredDescendants": 0,
            "active": true,
            "effectiveTime": "20020131",
            "module": "900000000000012004"
          },
          "acceptability": {
            "conceptId": "900000000000548007",
            "defaultTerm": "Preferred (foundation metadata concept)",
            "definitionStatus": "Primitive",
            "statedDescendants": 0,
            "inferredDescendants": 0,
            "active": true,
            "effectiveTime": "20020131",
            "module": "900000000000012004"
          },
          "uuid": "d2434cbf-d6ff-5cb2-a175-70ed49ddda27",
          "active": true,
          "effectiveTime": "20020131",
          "module": "900000000000207008"
        }
      ],
      "active": true,
      "effectiveTime": "20170731",
      "module": "900000000000207008"
    }
  ],
  "relationships": [
    {
      "type": {
        "conceptId": "116680003",
        "defaultTerm": "Is a (attribute)",
        "definitionStatus": "Primitive",
        "statedDescendants": 0,
        "inferredDescendants": 0,
        "active": true,
        "effectiveTime": "20110131",
        "module": "900000000000012004"
      },
      "target": {
        "conceptId": "76712006",
        "defaultTerm": "Disorder of digestive organ (disorder)",
        "definitionStatus": "Fully defined",
        "statedDescendants": 0,
        "inferredDescendants": 7695,
        "active": true,
        "effectiveTime": "20020131",
        "module": "900000000000207008"
      },
      "sourceId": "6215006",
      "groupId": 0,
      "charType": {
        "conceptId": "900000000000011006",
        "defaultTerm": "Inferred relationship (core metadata concept)",
        "definitionStatus": "Primitive",
        "statedDescendants": 0,
        "inferredDescendants": 0,
        "active": true,
        "effectiveTime": "20020131",
        "module": "900000000000012004"
      },
      "modifier": "Existential restriction",
      "targetMemberships": [
        "999002571000000104"
      ],
      "active": false,
      "effectiveTime": "20030731",
      "module": "900000000000207008"
    },
    {
      "type": {
        "conceptId": "116680003",
        "defaultTerm": "Is a (attribute)",
        "definitionStatus": "Primitive",
        "statedDescendants": 0,
        "inferredDescendants": 0,
        "active": true,
        "effectiveTime": "20110131",
        "module": "900000000000012004"
      },
      "target": {
        "conceptId": "128482007",
        "defaultTerm": "Acute inflammatory disease (disorder)",
        "definitionStatus": "Fully defined",
        "statedDescendants": 0,
        "inferredDescendants": 1190,
        "active": true,
        "effectiveTime": "20020131",
        "module": "900000000000207008"
      },
      "sourceId": "6215006",
      "groupId": 0,
      "charType": {
        "conceptId": "900000000000011006",
        "defaultTerm": "Inferred relationship (core metadata concept)",
        "definitionStatus": "Primitive",
        "statedDescendants": 0,
        "inferredDescendants": 0,
        "active": true,
        "effectiveTime": "20020131",
        "module": "900000000000012004"
      },
      "modifier": "Existential restriction",
      "targetMemberships": [
        "1127601000000107"
      ],
      "active": true,
      "effectiveTime": "20210131",
      "module": "900000000000207008"
    },
    {
      "type": {
        "conceptId": "116680003",
        "defaultTerm": "Is a (attribute)",
        "definitionStatus": "Primitive",
        "statedDescendants": 0,
        "inferredDescendants": 0,
        "active": true,
        "effectiveTime": "20110131",
        "module": "900000000000012004"
      },
      "target": {
        "conceptId": "82403002",
        "defaultTerm": "Cholangitis (disorder)",
        "definitionStatus": "Fully defined",
        "statedDescendants": 0,
        "inferredDescendants": 90,
        "active": true,
        "effectiveTime": "20020131",
        "module": "900000000000207008"
      },
      "sourceId": "6215006",
      "groupId": 0,
      "charType": {
        "conceptId": "900000000000011006",
        "defaultTerm": "Inferred relationship (core metadata concept)",
        "definitionStatus": "Primitive",
        "statedDescendants": 0,
        "inferredDescendants": 0,
        "active": true,
        "effectiveTime": "20020131",
        "module": "900000000000012004"
      },
      "modifier": "Existential restriction",
      "targetMemberships": [
        "1127601000000107"
      ],
      "active": true,
      "effectiveTime": "20020131",
      "module": "900000000000207008"
    },
    {
      "type": {
        "conceptId": "116680003",
        "defaultTerm": "Is a (attribute)",
        "definitionStatus": "Primitive",
        "statedDescendants": 0,
        "inferredDescendants": 0,
        "active": true,
        "effectiveTime": "20110131",
        "module": "900000000000012004"
      },
      "target": {
        "conceptId": "127321000",
        "defaultTerm": "Acute digestive system disorder (disorder)",
        "definitionStatus": "Fully defined",
        "statedDescendants": 0,
        "inferredDescendants": 317,
        "active": true,
        "effectiveTime": "20020131",
        "module": "900000000000207008"
      },
      "sourceId": "6215006",
      "groupId": 0,
      "charType": {
        "conceptId": "900000000000011006",
        "defaultTerm": "Inferred relationship (core metadata concept)",
        "definitionStatus": "Primitive",
        "statedDescendants": 0,
        "inferredDescendants": 0,
        "active": true,
        "effectiveTime": "20020131",
        "module": "900000000000012004"
      },
      "modifier": "Existential restriction",
      "targetMemberships": [
        "1127601000000107"
      ],
      "active": true,
      "effectiveTime": "20020131",
      "module": "900000000000207008"
    },
    {
      "type": {
        "conceptId": "260908002",
        "defaultTerm": "Course (attribute)",
        "definitionStatus": "Primitive",
        "statedDescendants": 0,
        "inferredDescendants": 0,
        "active": false,
        "effectiveTime": "20070131",
        "module": "900000000000207008"
      },
      "target": {
        "conceptId": "53737009",
        "defaultTerm": "Acute (qualifier value)",
        "definitionStatus": "Primitive",
        "statedDescendants": 0,
        "inferredDescendants": 0,
        "active": false,
        "effectiveTime": "20070131",
        "module": "900000000000207008"
      },
      "sourceId": "6215006",
      "groupId": 0,
      "charType": {
        "conceptId": "900000000000011006",
        "defaultTerm": "Inferred relationship (core metadata concept)",
        "definitionStatus": "Primitive",
        "statedDescendants": 0,
        "inferredDescendants": 0,
        "active": true,
        "effectiveTime": "20020131",
        "module": "900000000000012004"
      },
      "modifier": "Existential restriction",
      "active": false,
      "effectiveTime": "20020731",
      "module": "900000000000207008"
    },
    {
      "type": {
        "conceptId": "363698007",
        "defaultTerm": "Finding site (attribute)",
        "definitionStatus": "Primitive",
        "statedDescendants": 0,
        "inferredDescendants": 0,
        "active": true,
        "effectiveTime": "20110131",
        "module": "900000000000012004"
      },
      "target": {
        "conceptId": "28273000",
        "defaultTerm": "Bile duct structure (body structure)",
        "definitionStatus": "Primitive",
        "statedDescendants": 0,
        "inferredDescendants": 106,
        "active": true,
        "effectiveTime": "20020131",
        "module": "900000000000207008"
      },
      "sourceId": "6215006",
      "groupId": 1,
      "charType": {
        "conceptId": "900000000000011006",
        "defaultTerm": "Inferred relationship (core metadata concept)",
        "definitionStatus": "Primitive",
        "statedDescendants": 0,
        "inferredDescendants": 0,
        "active": true,
        "effectiveTime": "20020131",
        "module": "900000000000012004"
      },
      "modifier": "Existential restriction",
      "targetMemberships": [
        "999003151000000105"
      ],
      "active": false,
      "effectiveTime": "20080731",
      "module": "900000000000207008"
    },
    {
      "type": {
        "conceptId": "363698007",
        "defaultTerm": "Finding site (attribute)",
        "definitionStatus": "Primitive",
        "statedDescendants": 0,
        "inferredDescendants": 0,
        "active": true,
        "effectiveTime": "20110131",
        "module": "900000000000012004"
      },
      "target": {
        "conceptId": "34707002",
        "defaultTerm": "Structure of biliary tree (body structure)",
        "definitionStatus": "Primitive",
        "statedDescendants": 0,
        "inferredDescendants": 152,
        "active": true,
        "effectiveTime": "20020131",
        "module": "900000000000207008"
      },
      "sourceId": "6215006",
      "groupId": 1,
      "charType": {
        "conceptId": "900000000000011006",
        "defaultTerm": "Inferred relationship (core metadata concept)",
        "definitionStatus": "Primitive",
        "statedDescendants": 0,
        "inferredDescendants": 0,
        "active": true,
        "effectiveTime": "20020131",
        "module": "900000000000012004"
      },
      "modifier": "Existential restriction",
      "targetMemberships": [
        "999003151000000105"
      ],
      "active": false,
      "effectiveTime": "20030131",
      "module": "900000000000207008"
    },
    {
      "type": {
        "conceptId": "116676008",
        "defaultTerm": "Associated morphology (attribute)",
        "definitionStatus": "Primitive",
        "statedDescendants": 0,
        "inferredDescendants": 0,
        "active": true,
        "effectiveTime": "20110131",
        "module": "900000000000012004"
      },
      "target": {
        "conceptId": "23583003",
        "defaultTerm": "Inflammation (morphologic abnormality)",
        "definitionStatus": "Primitive",
        "statedDescendants": 0,
        "inferredDescendants": 0,
        "active": false,
        "effectiveTime": "20200131",
        "module": "900000000000207008"
      },
      "sourceId": "6215006",
      "groupId": 1,
      "charType": {
        "conceptId": "900000000000011006",
        "defaultTerm": "Inferred relationship (core metadata concept)",
        "definitionStatus": "Primitive",
        "statedDescendants": 0,
        "inferredDescendants": 0,
        "active": true,
        "effectiveTime": "20020131",
        "module": "900000000000012004"
      },
      "modifier": "Existential restriction",
      "active": false,
      "effectiveTime": "20040731",
      "module": "900000000000207008"
    },
    {
      "type": {
        "conceptId": "246100006",
        "defaultTerm": "Onset (attribute)",
        "definitionStatus": "Primitive",
        "statedDescendants": 0,
        "inferredDescendants": 0,
        "active": false,
        "effectiveTime": "20070131",
        "module": "900000000000207008"
      },
      "target": {
        "conceptId": "373933003",
        "defaultTerm": "Acute onset (qualifier value)",
        "definitionStatus": "Primitive",
        "statedDescendants": 0,
        "inferredDescendants": 0,
        "active": false,
        "effectiveTime": "20220930",
        "module": "900000000000207008"
      },
      "sourceId": "6215006",
      "groupId": 0,
      "charType": {
        "conceptId": "900000000000011006",
        "defaultTerm": "Inferred relationship (core metadata concept)",
        "definitionStatus": "Primitive",
        "statedDescendants": 0,
        "inferredDescendants": 0,
        "active": true,
        "effectiveTime": "20020131",
        "module": "900000000000012004"
      },
      "modifier": "Existential restriction",
      "active": false,
      "effectiveTime": "20030131",
      "module": "900000000000207008"
    },
    {
      "type": {
        "conceptId": "116680003",
        "defaultTerm": "Is a (attribute)",
        "definitionStatus": "Primitive",
        "statedDescendants": 0,
        "inferredDescendants": 0,
        "active": true,
        "effectiveTime": "20110131",
        "module": "900000000000012004"
      },
      "target": {
        "conceptId": "128999004",
        "defaultTerm": "Inflammatory disorder of digestive tract (disorder)",
        "definitionStatus": "Fully defined",
        "statedDescendants": 0,
        "inferredDescendants": 1150,
        "active": true,
        "effectiveTime": "20020131",
        "module": "900000000000207008"
      },
      "sourceId": "6215006",
      "groupId": 0,
      "charType": {
        "conceptId": "900000000000011006",
        "defaultTerm": "Inferred relationship (core metadata concept)",
        "definitionStatus": "Primitive",
        "statedDescendants": 0,
        "inferredDescendants": 0,
        "active": true,
        "effectiveTime": "20020131",
        "module": "900000000000012004"
      },
      "modifier": "Existential restriction",
      "targetMemberships": [
        "1127601000000107"
      ],
      "active": false,
      "effectiveTime": "20030731",
      "module": "900000000000207008"
    },
    {
      "type": {
        "conceptId": "116680003",
        "defaultTerm": "Is a (attribute)",
        "definitionStatus": "Primitive",
        "statedDescendants": 0,
        "inferredDescendants": 0,
        "active": true,
        "effectiveTime": "20110131",
        "module": "900000000000012004"
      },
      "target": {
        "conceptId": "363169009",
        "defaultTerm": "Inflammation of specific body organs (disorder)",
        "definitionStatus": "Fully defined",
        "statedDescendants": 0,
        "inferredDescendants": 8416,
        "active": true,
        "effectiveTime": "20020131",
        "module": "900000000000207008"
      },
      "sourceId": "6215006",
      "groupId": 0,
      "charType": {
        "conceptId": "900000000000011006",
        "defaultTerm": "Inferred relationship (core metadata concept)",
        "definitionStatus": "Primitive",
        "statedDescendants": 0,
        "inferredDescendants": 0,
        "active": true,
        "effectiveTime": "20020131",
        "module": "900000000000012004"
      },
      "modifier": "Existential restriction",
      "targetMemberships": [
        "999002571000000104"
      ],
      "active": false,
      "effectiveTime": "20200131",
      "module": "900000000000207008"
    },
    {
      "type": {
        "conceptId": "260908002",
        "defaultTerm": "Course (attribute)",
        "definitionStatus": "Primitive",
        "statedDescendants": 0,
        "inferredDescendants": 0,
        "active": false,
        "effectiveTime": "20070131",
        "module": "900000000000207008"
      },
      "target": {
        "conceptId": "53737009",
        "defaultTerm": "Acute (qualifier value)",
        "definitionStatus": "Primitive",
        "statedDescendants": 0,
        "inferredDescendants": 0,
        "active": false,
        "effectiveTime": "20070131",
        "module": "900000000000207008"
      },
      "sourceId": "6215006",
      "groupId": 0,
      "charType": {
        "conceptId": "900000000000011006",
        "defaultTerm": "Inferred relationship (core metadata concept)",
        "definitionStatus": "Primitive",
        "statedDescendants": 0,
        "inferredDescendants": 0,
        "active": true,
        "effectiveTime": "20020131",
        "module": "900000000000012004"
      },
      "modifier": "Existential restriction",
      "active": false,
      "effectiveTime": "20070131",
      "module": "900000000000207008"
    },
    {
      "type": {
        "conceptId": "116680003",
        "defaultTerm": "Is a (attribute)",
        "definitionStatus": "Primitive",
        "statedDescendants": 0,
        "inferredDescendants": 0,
        "active": true,
        "effectiveTime": "20110131",
        "module": "900000000000012004"
      },
      "target": {
        "conceptId": "118926004",
        "defaultTerm": "Disorder of bile duct (disorder)",
        "definitionStatus": "Fully defined",
        "statedDescendants": 0,
        "inferredDescendants": 264,
        "active": true,
        "effectiveTime": "20040731",
        "module": "900000000000207008"
      },
      "sourceId": "6215006",
      "groupId": 0,
      "charType": {
        "conceptId": "900000000000011006",
        "defaultTerm": "Inferred relationship (core metadata concept)",
        "definitionStatus": "Primitive",
        "statedDescendants": 0,
        "inferredDescendants": 0,
        "active": true,
        "effectiveTime": "20020131",
        "module": "900000000000012004"
      },
      "modifier": "Existential restriction",
      "targetMemberships": [
        "999002571000000104"
      ],
      "active": false,
      "effectiveTime": "20180131",
      "module": "900000000000207008"
    },
    {
      "type": {
        "conceptId": "116676008",
        "defaultTerm": "Associated morphology (attribute)",
        "definitionStatus": "Primitive",
        "statedDescendants": 0,
        "inferredDescendants": 0,
        "active": true,
        "effectiveTime": "20110131",
        "module": "900000000000012004"
      },
      "target": {
        "conceptId": "4532008",
        "defaultTerm": "Acute inflammation (morphologic abnormality)",
        "definitionStatus": "Primitive",
        "statedDescendants": 0,
        "inferredDescendants": 23,
        "active": true,
        "effectiveTime": "20020131",
        "module": "900000000000207008"
      },
      "sourceId": "6215006",
      "groupId": 1,
      "charType": {
        "conceptId": "900000000000011006",
        "defaultTerm": "Inferred relationship (core metadata concept)",
        "definitionStatus": "Primitive",
        "statedDescendants": 0,
        "inferredDescendants": 0,
        "active": true,
        "effectiveTime": "20020131",
        "module": "900000000000012004"
      },
      "modifier": "Existential restriction",
      "targetMemberships": [
        "999003141000000107"
      ],
      "active": false,
      "effectiveTime": "20080731",
      "module": "900000000000207008"
    },
    {
      "type": {
        "conceptId": "263502005",
        "defaultTerm": "Clinical course (attribute)",
        "definitionStatus": "Primitive",
        "statedDescendants": 0,
        "inferredDescendants": 0,
        "active": true,
        "effectiveTime": "20110131",
        "module": "900000000000012004"
      },
      "target": {
        "conceptId": "424124008",
        "defaultTerm": "Sudden onset AND/OR short duration (qualifier value)",
        "definitionStatus": "Primitive",
        "statedDescendants": 0,
        "inferredDescendants": 7,
        "active": true,
        "effectiveTime": "20070131",
        "module": "900000000000207008"
      },
      "sourceId": "6215006",
      "groupId": 1,
      "charType": {
        "conceptId": "900000000000011006",
        "defaultTerm": "Inferred relationship (core metadata concept)",
        "definitionStatus": "Primitive",
        "statedDescendants": 0,
        "inferredDescendants": 0,
        "active": true,
        "effectiveTime": "20020131",
        "module": "900000000000012004"
      },
      "modifier": "Existential restriction",
      "active": true,
      "effectiveTime": "20190731",
      "module": "900000000000207008"
    },
    {
      "type": {
        "conceptId": "363698007",
        "defaultTerm": "Finding site (attribute)",
        "definitionStatus": "Primitive",
        "statedDescendants": 0,
        "inferredDescendants": 0,
        "active": true,
        "effectiveTime": "20110131",
        "module": "900000000000012004"
      },
      "target": {
        "conceptId": "28273000",
        "defaultTerm": "Bile duct structure (body structure)",
        "definitionStatus": "Primitive",
        "statedDescendants": 0,
        "inferredDescendants": 106,
        "active": true,
        "effectiveTime": "20020131",
        "module": "900000000000207008"
      },
      "sourceId": "6215006",
      "groupId": 1,
      "charType": {
        "conceptId": "900000000000011006",
        "defaultTerm": "Inferred relationship (core metadata concept)",
        "definitionStatus": "Primitive",
        "statedDescendants": 0,
        "inferredDescendants": 0,
        "active": true,
        "effectiveTime": "20020131",
        "module": "900000000000012004"
      },
      "modifier": "Existential restriction",
      "targetMemberships": [
        "999003151000000105"
      ],
      "active": false,
      "effectiveTime": "20180131",
      "module": "900000000000207008"
    },
    {
      "type": {
        "conceptId": "116676008",
        "defaultTerm": "Associated morphology (attribute)",
        "definitionStatus": "Primitive",
        "statedDescendants": 0,
        "inferredDescendants": 0,
        "active": true,
        "effectiveTime": "20110131",
        "module": "900000000000012004"
      },
      "target": {
        "conceptId": "4532008",
        "defaultTerm": "Acute inflammation (morphologic abnormality)",
        "definitionStatus": "Primitive",
        "statedDescendants": 0,
        "inferredDescendants": 23,
        "active": true,
        "effectiveTime": "20020131",
        "module": "900000000000207008"
      },
      "sourceId": "6215006",
      "groupId": 1,
      "charType": {
        "conceptId": "900000000000011006",
        "defaultTerm": "Inferred relationship (core metadata concept)",
        "definitionStatus": "Primitive",
        "statedDescendants": 0,
        "inferredDescendants": 0,
        "active": true,
        "effectiveTime": "20020131",
        "module": "900000000000012004"
      },
      "modifier": "Existential restriction",
      "targetMemberships": [
        "999003141000000107"
      ],
      "active": false,
      "effectiveTime": "20180131",
      "module": "900000000000207008"
    },
    {
      "type": {
        "conceptId": "116676008",
        "defaultTerm": "Associated morphology (attribute)",
        "definitionStatus": "Primitive",
        "statedDescendants": 0,
        "inferredDescendants": 0,
        "active": true,
        "effectiveTime": "20110131",
        "module": "900000000000012004"
      },
      "target": {
        "conceptId": "23583003",
        "defaultTerm": "Inflammation (morphologic abnormality)",
        "definitionStatus": "Primitive",
        "statedDescendants": 0,
        "inferredDescendants": 0,
        "active": false,
        "effectiveTime": "20200131",
        "module": "900000000000207008"
      },
      "sourceId": "6215006",
      "groupId": 2,
      "charType": {
        "conceptId": "900000000000011006",
        "defaultTerm": "Inferred relationship (core metadata concept)",
        "definitionStatus": "Primitive",
        "statedDescendants": 0,
        "inferredDescendants": 0,
        "active": true,
        "effectiveTime": "20020131",
        "module": "900000000000012004"
      },
      "modifier": "Existential restriction",
      "active": false,
      "effectiveTime": "20200131",
      "module": "900000000000207008"
    },
    {
      "type": {
        "conceptId": "363698007",
        "defaultTerm": "Finding site (attribute)",
        "definitionStatus": "Primitive",
        "statedDescendants": 0,
        "inferredDescendants": 0,
        "active": true,
        "effectiveTime": "20110131",
        "module": "900000000000012004"
      },
      "target": {
        "conceptId": "34707002",
        "defaultTerm": "Structure of biliary tree (body structure)",
        "definitionStatus": "Primitive",
        "statedDescendants": 0,
        "inferredDescendants": 152,
        "active": true,
        "effectiveTime": "20020131",
        "module": "900000000000207008"
      },
      "sourceId": "6215006",
      "groupId": 2,
      "charType": {
        "conceptId": "900000000000011006",
        "defaultTerm": "Inferred relationship (core metadata concept)",
        "definitionStatus": "Primitive",
        "statedDescendants": 0,
        "inferredDescendants": 0,
        "active": true,
        "effectiveTime": "20020131",
        "module": "900000000000012004"
      },
      "modifier": "Existential restriction",
      "targetMemberships": [
        "999003151000000105"
      ],
      "active": true,
      "effectiveTime": "20180131",
      "module": "900000000000207008"
    },
    {
      "type": {
        "conceptId": "116676008",
        "defaultTerm": "Associated morphology (attribute)",
        "definitionStatus": "Primitive",
        "statedDescendants": 0,
        "inferredDescendants": 0,
        "active": true,
        "effectiveTime": "20110131",
        "module": "900000000000012004"
      },
      "target": {
        "conceptId": "409774005",
        "defaultTerm": "Inflammatory morphology (morphologic abnormality)",
        "definitionStatus": "Primitive",
        "statedDescendants": 0,
        "inferredDescendants": 197,
        "active": true,
        "effectiveTime": "20040731",
        "module": "900000000000207008"
      },
      "sourceId": "6215006",
      "groupId": 2,
      "charType": {
        "conceptId": "900000000000011006",
        "defaultTerm": "Inferred relationship (core metadata concept)",
        "definitionStatus": "Primitive",
        "statedDescendants": 0,
        "inferredDescendants": 0,
        "active": true,
        "effectiveTime": "20020131",
        "module": "900000000000012004"
      },
      "modifier": "Existential restriction",
      "targetMemberships": [
        "999003141000000107"
      ],
      "active": true,
      "effectiveTime": "20200131",
      "module": "900000000000207008"
    }
  ],
  "isLeafInferred": false,
  "isLeafStated": true,
  "fsn": "Acute cholangitis (disorder)",
  "conceptId": "6215006",
  "defaultTerm": "Acute cholangitis (disorder)",
  "definitionStatus": "Fully defined",
  "statedDescendants": 0,
  "inferredDescendants": 20,
  "active": true,
  "effectiveTime": "20020131",
  "module": "900000000000207008"
}